pyray_tompy/__init__.py
pyray_tompy/camera.py
pyray_tompy/color.py
pyray_tompy/cursor.py
pyray_tompy/drawing.py
pyray_tompy/keyboard.py
pyray_tompy/program.py
pyray_tompy/time.py
pyray_tompy/window.py
pyray_tompy-2025.10.10.18.36.dist-info/METADATA
pyray_tompy-2025.10.10.18.36.dist-info/WHEEL
pyray_tompy-2025.10.10.18.36.dist-info/RECORD
