Metadata-Version: 2.4
Name: pyray-tompy
Version: 2025.10.10.18.36
Summary: Pyray wrappers for tompy projects
Author: tompy
Classifier: Development Status :: 3 - Alpha
Classifier: Intended Audience :: Developers
Classifier: License :: OSI Approved :: GNU General Public License v3 (GPLv3)
Classifier: Operating System :: OS Independent
Classifier: Programming Language :: Python :: 3.11
Requires-Python: >=3.11
Requires-Dist: raylib>=5.5.0.3
Requires-Dist: vector-tompy>=2025.09.11.16.32
